[
	{
		"mevkii": "GB",
		"adi": "Ayite",
		"aciklama": "CEZALI (1)",
		"durum": "cezalılar"
	},
	{
		"mevkii": "GS",
		"adi": "Luyindama",
		"aciklama": "CEZALI (1)",
		"durum": "cezalılar"
	},
	{
		"mevkii": "GS",
		"adi": "Yedlin",
		"aciklama": "CEZALI (1)",
		"durum": "cezalılar"
	},
	{
		"mevkii": "GS",
		"adi": "Marcao",
		"aciklama": "CEZALI (1)",
		"durum": "cezalılar"
	},
	{
		"mevkii": "MLT",
		"adi": "Hadebe",
		"aciklama": "CEZALI (1)",
		"durum": "cezalılar"
	},
	{
		"mevkii": "AG",
		"adi": "Korcan",
		"aciklama": "SAKAT",
		"durum": "sakatlar"
	},
	{
		"mevkii": "AG",
		"adi": "Atakan",
		"aciklama": "(3 Hafta) SAKAT",
		"durum": "sakatlar"
	},
	{
		"mevkii": "ALS",
		"adi": "Kadzior",
		"aciklama": "SAKAT",
		"durum": "sakatlar"
	},
	{
		"mevkii": "ALS",
		"adi": "Caulker",
		"aciklama": "SAKAT",
		"durum": "sakatlar"
	},
	{
		"mevkii": "ANT",
		"adi": "Ufuk Akyol",
		"aciklama": "SAKAT",
		"durum": "sakatlar"
	},
	{
		"mevkii": "BJK",
		"adi": "Cenk Tosun",
		"aciklama": "Belirsiz",
		"durum": "sakatlar"
	},
	{
		"mevkii": "BJK",
		"adi": "Gökhan Töre",
		"aciklama": "SAKAT",
		"durum": "sakatlar"
	},
	{
		"mevkii": "BJK",
		"adi": "Montero",
		"aciklama": "SAKAT",
		"durum": "sakatlar"
	},
	{
		"mevkii": "CRZ",
		"adi": "Remy",
		"aciklama": "SAKAT",
		"durum": "sakatlar"
	},
	{
		"mevkii": "CRZ",
		"adi": "Alberk Koç",
		"aciklama": "SAKAT",
		"durum": "sakatlar"
	},
	{
		"mevkii": "CRZ",
		"adi": "Donsah",
		"aciklama": "SAKAT",
		"durum": "sakatlar"
	},
	{
		"mevkii": "DNZ",
		"adi": "Ahmed Yasin",
		"aciklama": "SAKAT",
		"durum": "sakatlar"
	},
	{
		"mevkii": "DNZ",
		"adi": "Özgür Çek",
		"aciklama": "SAKAT",
		"durum": "sakatlar"
	},
	{
		"mevkii": "ERZ",
		"adi": "Gomes",
		"aciklama": "SAKAT",
		"durum": "sakatlar"
	},
	{
		"mevkii": "ERZ",
		"adi": "Oltan",
		"aciklama": "SAKAT",
		"durum": "sakatlar"
	},
	{
		"mevkii": "FB",
		"adi": "Gökhan Gönül",
		"aciklama": "SAKAT",
		"durum": "sakatlar"
	},
	{
		"mevkii": "FB",
		"adi": "Mesut Özil",
		"aciklama": "SAKAT",
		"durum": "sakatlar"
	},
	{
		"mevkii": "FB",
		"adi": "Sadık",
		"aciklama": "SAKAT",
		"durum": "sakatlar"
	},
	{
		"mevkii": "FB",
		"adi": "Perotti",
		"aciklama": "SAKAT",
		"durum": "sakatlar"
	},
	{
		"mevkii": "GB",
		"adi": "Rahmetullah",
		"aciklama": "SAKAT",
		"durum": "sakatlar"
	},
	{
		"mevkii": "GB",
		"adi": "Stancu",
		"aciklama": "(2 Hafta) SAKAT",
		"durum": "sakatlar"
	},
	{
		"mevkii": "GB",
		"adi": "Toure",
		"aciklama": "(4 Hafta) SAKAT",
		"durum": "sakatlar"
	},
	{
		"mevkii": "GB",
		"adi": "Giovanni Sio",
		"aciklama": "(4 Hafta) SAKAT",
		"durum": "sakatlar"
	},
	{
		"mevkii": "GFK",
		"adi": "Djilobodji",
		"aciklama": "SAKAT",
		"durum": "sakatlar"
	},
	{
		"mevkii": "GFK",
		"adi": "Güray Vural",
		"aciklama": "SAKAT",
		"durum": "sakatlar"
	},
	{
		"mevkii": "GFK",
		"adi": "Kana Bıyık",
		"aciklama": "SAKAT",
		"durum": "sakatlar"
	},
	{
		"mevkii": "GFK",
		"adi": "Kozulj",
		"aciklama": "SAKAT",
		"durum": "sakatlar"
	},
	{
		"mevkii": "GOZ",
		"adi": "Tripic",
		"aciklama": "SAKAT",
		"durum": "sakatlar"
	},
	{
		"mevkii": "GS",
		"adi": "Donk",
		"aciklama": "SAKAT",
		"durum": "sakatlar"
	},
	{
		"mevkii": "GS",
		"adi": "Emre Taşdemir",
		"aciklama": "SAKAT",
		"durum": "sakatlar"
	},
	{
		"mevkii": "HTY",
		"adi": "Selim Ilgaz",
		"aciklama": "SAKAT",
		"durum": "sakatlar"
	},
	{
		"mevkii": "KAY",
		"adi": "Uğur Demirok",
		"aciklama": "SAKAT",
		"durum": "sakatlar"
	},
	{
		"mevkii": "KAY",
		"adi": "Alibec",
		"aciklama": "SAKAT",
		"durum": "sakatlar"
	},
	{
		"mevkii": "KAY",
		"adi": "Lung",
		"aciklama": "SAKAT",
		"durum": "sakatlar"
	},
	{
		"mevkii": "KON",
		"adi": "Volkan Fındıklı",
		"aciklama": "(1 Hafta) SAKAT",
		"durum": "sakatlar"
	},
	{
		"mevkii": "KON",
		"adi": "Alper Uludağ",
		"aciklama": "(6 Ay) SAKAT",
		"durum": "sakatlar"
	},
	{
		"mevkii": "KSP",
		"adi": "Hodzic",
		"aciklama": "Belirsiz",
		"durum": "sakatlar"
	},
	{
		"mevkii": "KSP",
		"adi": "Yusuf Erdoğan",
		"aciklama": "SAKAT",
		"durum": "sakatlar"
	},
	{
		"mevkii": "KSP",
		"adi": "Tarkan Serbest",
		"aciklama": "SAKAT",
		"durum": "sakatlar"
	},
	{
		"mevkii": "KSP",
		"adi": "Jeanvier",
		"aciklama": "(8 Ay) SAKAT",
		"durum": "sakatlar"
	},
	{
		"mevkii": "MED",
		"adi": "Gulbrandsen",
		"aciklama": "SAKAT",
		"durum": "sakatlar"
	},
	{
		"mevkii": "MED",
		"adi": "Duarte",
		"aciklama": "SAKAT",
		"durum": "sakatlar"
	},
	{
		"mevkii": "MED",
		"adi": "Chadli",
		"aciklama": "SAKAT",
		"durum": "sakatlar"
	},
	{
		"mevkii": "MED",
		"adi": "Bolingoli",
		"aciklama": "SAKAT",
		"durum": "sakatlar"
	},
	{
		"mevkii": "MED",
		"adi": "Caiçara",
		"aciklama": "SAKAT",
		"durum": "sakatlar"
	},
	{
		"mevkii": "MLT",
		"adi": "Olcay Şahan",
		"aciklama": "SAKAT",
		"durum": "sakatlar"
	},
	{
		"mevkii": "SVS",
		"adi": "Appindangoye",
		"aciklama": "(4 Hafta) SAKAT",
		"durum": "sakatlar"
	},
	{
		"mevkii": "SVS",
		"adi": "Claudemir",
		"aciklama": "SAKAT",
		"durum": "sakatlar"
	},
	{
		"mevkii": "SVS",
		"adi": "Muammer",
		"aciklama": "SAKAT",
		"durum": "sakatlar"
	},
	{
		"mevkii": "SVS",
		"adi": "Rybalka",
		"aciklama": "SAKAT",
		"durum": "sakatlar"
	},
	{
		"mevkii": "SVS",
		"adi": "Caner",
		"aciklama": "SAKAT",
		"durum": "sakatlar"
	},
	{
		"mevkii": "TS",
		"adi": "Berat Özdemir",
		"aciklama": "SAKAT",
		"durum": "sakatlar"
	},
	{
		"mevkii": "TS",
		"adi": "Kamil Ahmet",
		"aciklama": "SAKAT",
		"durum": "sakatlar"
	},
	{
		"mevkii": "TS",
		"adi": "Abdülkadir Ö.",
		"aciklama": "(12 hafta) SAKAT",
		"durum": "sakatlar"
	},
	{
		"mevkii": "TS",
		"adi": "Trondsen",
		"aciklama": "SAKAT",
		"durum": "sakatlar"
	},
	{
		"mevkii": "BJK",
		"adi": "Douglas",
		"aciklama": "Kadro Dışı",
		"durum": "kadro dışı"
	},
	{
		"mevkii": "DNZ",
		"adi": "Varela",
		"aciklama": "Kadro Dışı",
		"durum": "kadro dışı"
	},
	{
		"mevkii": "ERZ",
		"adi": "Yaw Ackah",
		"aciklama": "Kadro Dışı",
		"durum": "kadro dışı"
	},
	{
		"mevkii": "KAY",
		"adi": "Fernandes",
		"aciklama": "Kadro Dışı",
		"durum": "kadro dışı"
	},
	{
		"mevkii": "KAY",
		"adi": "Kanga",
		"aciklama": "Kadro Dışı",
		"durum": "kadro dışı"
	},
	{
		"mevkii": "KAY",
		"adi": "Miguel Lopes",
		"aciklama": "Kadro Dışı",
		"durum": "kadro dışı"
	},
	{
		"mevkii": "KAY",
		"adi": "Manzala",
		"aciklama": "Kadro Dışı",
		"durum": "kadro dışı"
	},
	{
		"mevkii": "KSP",
		"adi": "Gerard Gohou",
		"aciklama": "Kadro Dışı",
		"durum": "kadro dışı"
	},
	{
		"mevkii": "KSP",
		"adi": "Koita",
		"aciklama": "Kadro Dışı",
		"durum": "kadro dışı"
	},
	{
		"mevkii": "TS",
		"adi": "Plaza",
		"aciklama": "Kadro Dışı",
		"durum": "kadro dışı"
	},
	{
		"mevkii": "AG",
		"adi": "Cebrail",
		"aciklama": "Sözleşme Feshi",
		"durum": "kadro dışı"
	},
	{
		"mevkii": "AG",
		"adi": "Luka Adzic",
		"aciklama": "Sözleşme Feshi",
		"durum": "kadro dışı"
	},
	{
		"mevkii": "ALS",
		"adi": "Ufuk Ceylan",
		"aciklama": "Sözleşme Feshi",
		"durum": "kadro dışı"
	},
	{
		"mevkii": "ERZ",
		"adi": "Sissoko",
		"aciklama": "Sözleşme Feshi",
		"durum": "kadro dışı"
	},
	{
		"mevkii": "ERZ",
		"adi": "Sadiku",
		"aciklama": "Sözleşme Feshi",
		"durum": "kadro dışı"
	},
	{
		"mevkii": "ERZ",
		"adi": "Rashad",
		"aciklama": "Sözleşme Feshi",
		"durum": "kadro dışı"
	},
	{
		"mevkii": "ERZ",
		"adi": "Farnolle",
		"aciklama": "Sözleşme Feshi",
		"durum": "kadro dışı"
	},
	{
		"mevkii": "ERZ",
		"adi": "Kaan Kanak",
		"aciklama": "Sözleşme Feshi",
		"durum": "kadro dışı"
	},
	{
		"mevkii": "ERZ",
		"adi": "Muhammedo Ba",
		"aciklama": "Sözleşme Feshi",
		"durum": "kadro dışı"
	},
	{
		"mevkii": "FKG",
		"adi": "Badou NDiaye",
		"aciklama": "Sözleşme Feshi",
		"durum": "kadro dışı"
	},
	{
		"mevkii": "FKG",
		"adi": "Lichaj",
		"aciklama": "Sözleşme Feshi",
		"durum": "kadro dışı"
	},
	{
		"mevkii": "FKG",
		"adi": "Zeki Yıldırım",
		"aciklama": "Sözleşme Feshi",
		"durum": "kadro dışı"
	},
	{
		"mevkii": "GS",
		"adi": "Belhanda",
		"aciklama": "Sözleşme Feshi",
		"durum": "kadro dışı"
	},
	{
		"mevkii": "KON",
		"adi": "Hurtado",
		"aciklama": "Sözleşme Feshi",
		"durum": "kadro dışı"
	},
	{
		"mevkii": "KSP",
		"adi": "Azad Toptik",
		"aciklama": "Sözleşme Feshi",
		"durum": "kadro dışı"
	},
	{
		"mevkii": "KSP",
		"adi": "Alan Carius",
		"aciklama": "Sözleşme Feshi",
		"durum": "kadro dışı"
	},
	{
		"mevkii": "MED",
		"adi": "Skrtel",
		"aciklama": "Sözleşme Feshi",
		"durum": "kadro dışı"
	}
]
